[
  {
    "name": "Phantasmal Flames Booster Box",
    "tcgPlayerId": "654137",
    "quantity": 2
  },
  {
    "name": "Mega Evolution Enhanced Booster Box",
    "tcgPlayerId": "644300",
    "quantity": 1
  },
  {
    "name": "Phantasmal Flames Pokemon Center Elite Trainer Box (Exclusive)",
    "tcgPlayerId": "654135",
    "quantity": 4
  },
  {
    "name": "Mega Evolution Pokemon Center Elite Trainer Box (Exclusive) [Mega Lucario]",
    "tcgPlayerId": "644282",
    "quantity": 2
  },
  {
    "name": "Mega Evolution Pokemon Center Elite Trainer Box (Exclusive) [Mega Gardevoir]",
    "tcgPlayerId": "648415",
    "quantity": 2
  },
  {
    "name": "Black Bolt Pokemon Center Elite Trainer Box (Exclusive)",
    "tcgPlayerId": "630687",
    "quantity": 2
  },
  {
    "name": "White Flare Pokemon Center Elite Trainer Box (Exclusive)",
    "tcgPlayerId": "630688",
    "quantity": 2
  },
  {
    "name": "Destined Rivals Elite Trainer Box",
    "tcgPlayerId": "624676",
    "quantity": 2
  },
  {
    "name": "Prismatic Evolutions Lucario ex & Tyranitar ex Premium Collection (Sam's Club)",
    "tcgPlayerId": "648365",
    "quantity": 1
  },
  {
    "name": "Leafeon VSTAR Special Collection",
    "tcgPlayerId": "256147",
    "quantity": 2
  },
  {
    "name": "Mega Evolution Elite Trainer Box [Mega Gardevoir]",
    "tcgPlayerId": "644279",
    "quantity": 1
  },
  {
    "name": "Holiday Calendar 2025",
    "tcgPlayerId": "639828",
    "quantity": 5
  },
  {
    "name": "Professor Juniper Premium Tournament Collection Box",
    "tcgPlayerId": "268713",
    "quantity": 2
  },
  {
    "name": "Surging Sparks Elite Trainer Box",
    "tcgPlayerId": "565630",
    "quantity": 8
  },
  {
    "name": "Twilight Masquerade Elite Trainer Box",
    "tcgPlayerId": "543845",
    "quantity": 5
  },
  {
    "name": "Prismatic Evolutions Booster Bundle",
    "tcgPlayerId": "600518",
    "quantity": 3
  },
  {
    "name": "Gem Pack Vol. 2 Booster Box (CN)",
    "tcgPlayerId": "",
    "quantity": 1
  },
  {
    "name": "Black Bolt Booster Bundle",
    "tcgPlayerId": "630431",
    "quantity": 15
  },
  {
    "name": "White Flare Booster Bundle",
    "tcgPlayerId": "630696",
    "quantity": 13
  },
  {
    "name": "Mega Evolution Booster Bundle",
    "tcgPlayerId": "644362",
    "quantity": 2
  },
  {
    "name": "Stellar Crown Booster Bundle",
    "tcgPlayerId": "557345",
    "quantity": 12
  },
  {
    "name": "White Flare Binder Collection",
    "tcgPlayerId": "630695",
    "quantity": 2
  },
  {
    "name": "Prismatic Evolutions Surprise Box",
    "tcgPlayerId": "593466",
    "quantity": 20
  },
  {
    "name": "Surging Sparks Booster Bundle",
    "tcgPlayerId": "565629",
    "quantity": 10
  },
  {
    "name": "Ogerpon ex Premium Collection",
    "tcgPlayerId": "576482",
    "quantity": 1
  },
  {
    "name": "Unova Victini Illustration Collection",
    "tcgPlayerId": "630615",
    "quantity": 4
  },
  {
    "name": "Paradox Rift Build & Battle Box",
    "tcgPlayerId": "514068",
    "quantity": 3
  },
  {
    "name": "Prismatic Evolutions 2Blister [Eevee]",
    "tcgPlayerId": "",
    "quantity": 1
  },
  {
    "name": "Mega Latias ex Box",
    "tcgPlayerId": "654188",
    "quantity": 1
  },
  {
    "name": "Black Bolt Tech Sticker Collection",
    "tcgPlayerId": "630614",
    "quantity": 4
  },
  {
    "name": "Prismatic Evolutions Poster Collection",
    "tcgPlayerId": "593359",
    "quantity": 14
  },
  {
    "name": "Pokemon - Poke Ball Tin - Poke Ball (Q4 2024)",
    "tcgPlayerId": "587365",
    "quantity": 5
  },
  {
    "name": "Pokemon - Poke Ball Tin - Moon Ball (Q4 2024)",
    "tcgPlayerId": "587369",
    "quantity": 3
  },
  {
    "name": "Silver Tempest Booster Pack",
    "tcgPlayerId": "283388",
    "quantity": 3
  },
  {
    "name": "Astral Radiance Sleeved Booster Pack",
    "tcgPlayerId": "265526",
    "quantity": 1
  },
  {
    "name": "Paldea Evolved Booster Pack",
    "tcgPlayerId": "493976",
    "quantity": 3
  },
  {
    "name": "Mega Evolution Sleeved Booster Pack",
    "tcgPlayerId": "644354",
    "quantity": 6
  },
  {
    "name": "Darkness Ablaze Booster Pack",
    "tcgPlayerId": "216852",
    "quantity": 1
  },
  {
    "name": "Paradox Rift Sleeved Booster Pack",
    "tcgPlayerId": "517210",
    "quantity": 3
  },
  {
    "name": "Stellar Crown Booster Pack",
    "tcgPlayerId": "557331",
    "quantity": 15
  },
  {
    "name": "Scarlet & Violet Booster Pack",
    "tcgPlayerId": "476451",
    "quantity": 3
  },
  {
    "name": "Temporal Forces Booster Pack",
    "tcgPlayerId": "532841",
    "quantity": 15
  },
  {
    "name": "Twilight Masquerade Booster Pack",
    "tcgPlayerId": "543843",
    "quantity": 13
  }
]
